secrets_manager/__init__.py
secrets_manager/secrets_manager.py
secrets_manager_aws-0.1.0.dist-info/licenses/LICENSE
secrets_manager_aws-0.1.0.dist-info/METADATA
secrets_manager_aws-0.1.0.dist-info/WHEEL
secrets_manager_aws-0.1.0.dist-info/entry_points.txt
secrets_manager_aws-0.1.0.dist-info/top_level.txt
secrets_manager_aws-0.1.0.dist-info/RECORD
