Metadata-Version: 2.4
Name: secrets-manager-aws
Version: 0.1.0
Summary: A tool to manage AWS Secrets Manager secrets using a temporary .env file edited in vim
Author-email: Arun Karthi Mani <developer.makk@gmail.com>
License: Copyright (c) 2025 Your Name
Requires-Python: >=3.9
License-File: LICENSE
Requires-Dist: boto3>=1.28.0
Dynamic: license-file
